minecraft_remapper/__init__.py
minecraft_remapper/__main__.py
minecraft_remapper/remapper.py
minecraft_remapper-1.1.0.dist-info/LICENSE
minecraft_remapper-1.1.0.dist-info/WHEEL
minecraft_remapper-1.1.0.dist-info/METADATA
minecraft_remapper-1.1.0.dist-info/RECORD
