Metadata-Version: 2.1
Name: minecraft_remapper
Version: 1.1.0
Summary: A Minecraft remapper for already deobfuscated forge mod source code.
Home-page: https://github.com/Nearata/minecraft-remapper
Author: Nearata
Author-email: nearata@protonmail.com
Requires-Python: >=3.9
Classifier: License :: OSI Approved :: MIT License
Classifier: Programming Language :: Python :: 3
Classifier: Programming Language :: Python :: 3 :: Only
Classifier: Programming Language :: Python :: 3.9
Requires-Dist: click ==8.0.1
Requires-Dist: colorama ==0.4.4
